market_basket_analysis/__init__.py
market_basket_analysis/association_rules.py
market_basket_analysis/main.py
market_basket_analysis/visualisation.py
market_basket_analysis-0.1.3.dist-info/LICENSE
market_basket_analysis-0.1.3.dist-info/METADATA
market_basket_analysis-0.1.3.dist-info/WHEEL
market_basket_analysis-0.1.3.dist-info/top_level.txt
market_basket_analysis-0.1.3.dist-info/RECORD
