Metadata-Version: 2.1
Name: market_basket_analysis
Version: 0.1.3
Summary: A market basket analysis package for data
Home-page: 
Author: Phalguni
Author-email: phalgunishenoy2002@gmail.com
Classifier: Programming Language :: Python :: 3
Classifier: License :: OSI Approved :: MIT License
Classifier: Operating System :: OS Independent
Requires-Python: >=3.6
License-File: LICENSE
